threadlepy/__init__.py
threadlepy/client.py
threadlepy/commands.py
threadlepy-0.0.2.dist-info/licenses/LICENSE
threadlepy-0.0.2.dist-info/METADATA
threadlepy-0.0.2.dist-info/WHEEL
threadlepy-0.0.2.dist-info/top_level.txt
threadlepy-0.0.2.dist-info/RECORD
