Metadata-Version: 2.4
Name: threadlepy
Version: 0.0.2
Summary: a Python client for Threadle
Author-email: Yukun Jiao <jiaoyukun1999@gmail.com>
License-Expression: MIT
Project-URL: Homepage, https://github.com/YukunJiao/threadlepy
Project-URL: Issues, https://github.com/YukunJiao/threadlepy/issues
Classifier: Programming Language :: Python :: 3
Classifier: Operating System :: OS Independent
Requires-Python: >=3.9
License-File: LICENSE
Dynamic: license-file
